sphinx_gated_directives/__init__.py
sphinx_gated_directives/_version.py
sphinx_gated_directives-1.0.2.dist-info/METADATA
sphinx_gated_directives-1.0.2.dist-info/WHEEL
sphinx_gated_directives-1.0.2.dist-info/licenses/LICENSE
sphinx_gated_directives-1.0.2.dist-info/RECORD
