Metadata-Version: 2.4
Name: sphinx-gated-directives
Version: 1.0.2
Summary: This package is an extension for Sphinx that creates a '-start' companion and a '-end' companion for every registered class-based directive.
Author-email: Dennis den Ouden-van der Horst <d.denouden-vanderhorst@tudelft.nl>
License: MIT License
License-File: LICENSE
Requires-Python: >=3.10
Requires-Dist: sphinx
